html_to_dash/__init__.py
html_to_dash/helper.py
html_to_dash/main.py
html_to_dash-0.2.7.dist-info/LICENSE
html_to_dash-0.2.7.dist-info/METADATA
html_to_dash-0.2.7.dist-info/WHEEL
html_to_dash-0.2.7.dist-info/top_level.txt
html_to_dash-0.2.7.dist-info/RECORD
