Metadata-Version: 2.1
Name: html-to-dash
Version: 0.2.7
Summary: Convert HTML to dash format.
Home-page: https://github.com/PierXuY/html-to-dash
Author: PierXuY
Keywords: html,dash
Classifier: Programming Language :: Python :: 3
Requires-Python: >=3.6
License-File: LICENSE
Requires-Dist: dash
Requires-Dist: black
Requires-Dist: lxml
Requires-Dist: dash-svg
Requires-Dist: cssutils
